{
  "configurations": [
    {
      "title_cleanup_regex": "^(.*?)\\s+\u2013",
      "ignore": [
        "a.headerlink",
        "ul.breadcrumb"
      ],
      "content_selectors": [
        "section.document"
      ],
      "content_sections": [
        "div.section"
      ],
      "content_scoring": {
        "learn": "6",
        "clients": "7",
        "integrations": "6",
        "api": "4",
        "clientdev": "3",
        "server": "2"
      },
      "skip_docs": [
        "sitemap",
        "search"
      ],
      "sources": [
        {
          "path": "",
          "section": "hosted"
        }
      ]
    }
  ]
}
